README.md
pyproject.toml
python/licere/__main__.py
python/licere/api.py
python/licere/constants.py
python/licere/document.py
python/licere/version.py
python/licere.egg-info/PKG-INFO
python/licere.egg-info/SOURCES.txt
python/licere.egg-info/dependency_links.txt
python/licere.egg-info/entry_points.txt
python/licere.egg-info/requires.txt
python/licere.egg-info/top_level.txt
python/licere/licenses/apache/__init__.py
python/licere/licenses/apache/apache.md.jinja
python/licere/licenses/apache/meta.py
python/licere/licenses/bsd/__init__.py
python/licere/licenses/bsd/meta.py
python/licere/licenses/mit/__init__.py
python/licere/licenses/mit/meta.py
python/licere/licenses/polyform/__init__.py
python/licere/licenses/polyform/meta.py
python/licere/licenses/polyform/polyform.md.jinja