Metadata-Version: 2.1
Name: licere
Version: 20240201
Summary: Generate licenses from templates.
Author: Nate Skulic, MetaCompany
Project-URL: Homepage, http://meta.company/go/licere
Project-URL: Documentation, http://meta.company/go/licere
Project-URL: Repository, http://sr.ht/~metacompany/licere
Requires-Python: >=3.9
Requires-Dist: toml
Requires-Dist: jinja2
